biogl/GxfParse.py
biogl/__init__.py
biogl/arg_info_header.py
biogl/byte_convert.py
biogl/coord_overlap.py
biogl/fasta_parse.py
biogl/file_hash.py
biogl/flex_open.py
biogl/get_runtime.py
biogl/is_fasta.py
biogl/label_info.py
biogl/random_seq.py
biogl/recursive_items.py
biogl/rev_comp.py
biogl/translate.py
biogl/window.py
biogl-2.4.0.dist-info/METADATA
biogl-2.4.0.dist-info/WHEEL
biogl-2.4.0.dist-info/top_level.txt
biogl-2.4.0.dist-info/RECORD
