Metadata-Version: 2.4
Name: biogl
Version: 2.4.0
Summary: A collection of (semi) useful bioinformatics functions
Author-email: Graham Larue <egrahamlarue@gmail.com>
License: MIT
Requires-Python: >=3.10
Requires-Dist: smart_open
